LICENSE
MANIFEST.in
README.md
foreman-host-builder.py
setup.py
fhb/__init__.py
fhb/config.py
fhb/imports.py
foreman_host_builder.egg-info/PKG-INFO
foreman_host_builder.egg-info/SOURCES.txt
foreman_host_builder.egg-info/dependency_links.txt
foreman_host_builder.egg-info/requires.txt
foreman_host_builder.egg-info/top_level.txt