Metadata-Version: 1.0
Name: foreman-host-builder
Version: 2.1
Summary: Build hosts in Foreman from a template file
Home-page: https://github.com/xnaveira/foreman-host-builder
Author: Xavier Naveira
Author-email: xnaveira@gmail.com
License: UNKNOWN
Platform: UNKNOWN
